IMC_library/__init__.py
IMC_library/convert_mcd.py
IMC_library/display_markers.py
IMC_library/function.py
IMC_library/visualize.py
tests/__init__.py
tests/test_functions.py
IMC_library-0.0.9.dist-info/METADATA
IMC_library-0.0.9.dist-info/WHEEL
IMC_library-0.0.9.dist-info/entry_points.txt
IMC_library-0.0.9.dist-info/top_level.txt
IMC_library-0.0.9.dist-info/RECORD
