Metadata-Version: 2.1
Name: IMC_library
Version: 0.0.9
Summary: library to analyse Imaging Mass Cytometry
Author: Gregoire Menard
Author-email: gregoire.menard.72@hotmail.fr
